<?xml version="1.0" encoding="utf-8"?>
<TextureAtlas imagePath="release-me-sprites-FLEETWAY-VA.png">
	<!-- Created with Adobe Animate version 21.0.6.41649 -->
	<!-- http://www.adobe.com/products/animate.html -->
	<SubTexture name="ENOUGH instance 10000" x="0" y="0" width="892" height="1100"/>
	<SubTexture name="ENOUGH instance 10001" x="904" y="0" width="892" height="1100"/>
	<SubTexture name="ENOUGH instance 10002" x="1808" y="0" width="892" height="1100"/>
	<SubTexture name="ENOUGH instance 10003" x="2712" y="0" width="892" height="1100"/>
	<SubTexture name="ENOUGH instance 10004" x="3616" y="0" width="892" height="1100"/>
	<SubTexture name="ENOUGH instance 10005" x="4520" y="0" width="892" height="1100"/>
	<SubTexture name="ENOUGH instance 10006" x="5424" y="0" width="892" height="1100"/>
	<SubTexture name="ENOUGH instance 10007" x="6328" y="0" width="892" height="1100"/>
	<SubTexture name="ENOUGH instance 10008" x="7232" y="0" width="892" height="1100"/>
	<SubTexture name="ENOUGH instance 10009" x="0" y="1112" width="892" height="1100"/>
	<SubTexture name="ENOUGH instance 10010" x="904" y="1112" width="892" height="1100"/>
	<SubTexture name="ENOUGH instance 10011" x="1808" y="1112" width="892" height="1100"/>
	<SubTexture name="ENOUGH instance 10012" x="2712" y="1112" width="892" height="1100"/>
	<SubTexture name="ENOUGH instance 10013" x="3616" y="1112" width="892" height="1100"/>
	<SubTexture name="ENOUGH instance 10014" x="4520" y="1112" width="892" height="1100"/>
	<SubTexture name="ENOUGH instance 10015" x="2712" y="1112" width="892" height="1100"/>
	<SubTexture name="ENOUGH instance 10016" x="3616" y="1112" width="892" height="1100"/>
	<SubTexture name="ENOUGH instance 10017" x="4520" y="1112" width="892" height="1100"/>
	<SubTexture name="ENOUGH instance 10018" x="2712" y="1112" width="892" height="1100"/>
	<SubTexture name="ENOUGH instance 10019" x="3616" y="1112" width="892" height="1100"/>
	<SubTexture name="ENOUGH instance 10020" x="4520" y="1112" width="892" height="1100"/>
	<SubTexture name="LAUGH instance 10000" x="5424" y="1112" width="901" height="1202"/>
	<SubTexture name="LAUGH instance 10001" x="6337" y="1112" width="901" height="1202"/>
	<SubTexture name="LAUGH instance 10002" x="7250" y="1112" width="901" height="1202"/>
	<SubTexture name="LAUGH instance 10003" x="0" y="2326" width="901" height="1202"/>
	<SubTexture name="LAUGH instance 10004" x="913" y="2326" width="901" height="1202"/>
	<SubTexture name="LAUGH instance 10005" x="1826" y="2326" width="901" height="1202"/>
	<SubTexture name="LAUGH instance 10006" x="2739" y="2326" width="901" height="1202"/>
	<SubTexture name="LAUGH instance 10007" x="3652" y="2326" width="901" height="1202"/>
	<SubTexture name="LAUGH instance 10008" x="4565" y="2326" width="901" height="1202"/>
	<SubTexture name="LAUGH instance 10009" x="2739" y="2326" width="901" height="1202"/>
	<SubTexture name="LAUGH instance 10010" x="5478" y="2326" width="901" height="1202"/>
	<SubTexture name="LAUGH instance 10011" x="6391" y="2326" width="901" height="1202"/>
	<SubTexture name="LAUGH instance 10012" x="0" y="3540" width="901" height="1202"/>
	<SubTexture name="LAUGH instance 10013" x="5478" y="2326" width="901" height="1202"/>
	<SubTexture name="LAUGH instance 10014" x="1826" y="2326" width="901" height="1202"/>
	<SubTexture name="LAUGH instance 10015" x="0" y="3540" width="901" height="1202"/>
	<SubTexture name="LAUGH instance 10016" x="913" y="3540" width="901" height="1202"/>
	<SubTexture name="LAUGH instance 10017" x="1826" y="2326" width="901" height="1202"/>
	<SubTexture name="LAUGH instance 10018" x="2739" y="2326" width="901" height="1202"/>
	<SubTexture name="LAUGH instance 10019" x="1826" y="3540" width="901" height="1202"/>
	<SubTexture name="LAUGH instance 10020" x="2739" y="3540" width="901" height="1202"/>
	<SubTexture name="LAUGH instance 10021" x="3652" y="3540" width="901" height="1202"/>
	<SubTexture name="LAUGH instance 10022" x="4565" y="3540" width="901" height="1202"/>
	<SubTexture name="LAUGH instance 10023" x="5478" y="3540" width="901" height="1202"/>
	<SubTexture name="LAUGH instance 10024" x="6391" y="3540" width="901" height="1202"/>
	<SubTexture name="LAUGH instance 10025" x="0" y="4754" width="901" height="1202"/>
	<SubTexture name="LAUGH instance 10026" x="913" y="4754" width="901" height="1202"/>
	<SubTexture name="LAUGH instance 10027" x="1826" y="4754" width="901" height="1202"/>
	<SubTexture name="LAUGH instance 10028" x="2739" y="4754" width="901" height="1202"/>
	<SubTexture name="LAUGH instance 10029" x="913" y="4754" width="901" height="1202"/>
	<SubTexture name="LAUGH instance 10030" x="3652" y="4754" width="901" height="1202"/>
	<SubTexture name="LAUGH instance 10031" x="4565" y="4754" width="901" height="1202"/>
	<SubTexture name="LAUGH instance 10032" x="5478" y="4754" width="901" height="1202"/>
	<SubTexture name="LAUGH instance 10033" x="3652" y="4754" width="901" height="1202"/>
	<SubTexture name="LAUGH instance 10034" x="0" y="4754" width="901" height="1202"/>
	<SubTexture name="LAUGH instance 10035" x="913" y="4754" width="901" height="1202"/>
	<SubTexture name="LAUGH instance 10036" x="3652" y="4754" width="901" height="1202"/>
	<SubTexture name="LAUGH instance 10037" x="0" y="4754" width="901" height="1202"/>
	<SubTexture name="LAUGH instance 10038" x="913" y="4754" width="901" height="1202"/>
	<SubTexture name="LAUGH instance 10039" x="3652" y="4754" width="901" height="1202"/>
	<SubTexture name="grr instance 10000" x="6391" y="4754" width="706" height="1230"/>
	<SubTexture name="grr instance 10001" x="7109" y="4754" width="706" height="1230"/>
	<SubTexture name="grr instance 10002" x="0" y="5996" width="706" height="1230"/>
	<SubTexture name="grr instance 10003" x="718" y="5996" width="706" height="1230"/>
	<SubTexture name="grr instance 10004" x="1436" y="5996" width="706" height="1230"/>
	<SubTexture name="grr instance 10005" x="2154" y="5996" width="706" height="1230"/>
	<SubTexture name="grr instance 10006" x="2872" y="5996" width="706" height="1230"/>
	<SubTexture name="grr instance 10007" x="3590" y="5996" width="706" height="1230"/>
	<SubTexture name="grr instance 10008" x="4308" y="5996" width="706" height="1230"/>
	<SubTexture name="grr instance 10009" x="5026" y="5996" width="706" height="1230"/>
	<SubTexture name="grr instance 10010" x="3590" y="5996" width="706" height="1230"/>
	<SubTexture name="grr instance 10011" x="5744" y="5996" width="706" height="1230"/>
	<SubTexture name="grr instance 10012" x="5026" y="5996" width="706" height="1230"/>
	<SubTexture name="grr instance 10013" x="6462" y="5996" width="706" height="1230"/>
</TextureAtlas>
